EfficientSceneDetector/__init__.py
EfficientSceneDetector/sceneDetection.py
EfficientSceneDetector/helperFiles/__init__.py
EfficientSceneDetector/helperFiles/features.py
EfficientSceneDetector/helperFiles/model.h5
EfficientSceneDetector/helperFiles/params.py
EfficientSceneDetector/helperFiles/utils.py
EfficientSceneDetector/helperFiles/yam.py
EfficientSceneDetector/helperFiles/yam_class_map.csv
efficientscenedetector-0.0.12.dist-info/METADATA
efficientscenedetector-0.0.12.dist-info/WHEEL
efficientscenedetector-0.0.12.dist-info/licenses/LICENSE
efficientscenedetector-0.0.12.dist-info/RECORD
