Metadata-Version: 2.1
Name: EfficientSceneDetector
Version: 0.0.12
Summary: An Efficient Scene Detector
Project-URL: Homepage, https://github.com/akewarmayur/EfficientSceneDetector
Project-URL: Bug Tracker, https://github.com/akewarmayur/EfficientSceneDetector/issues
Author-email: Mayur Akewar <mayurakewar87@gmail.com>
License-File: LICENSE
Classifier: License :: OSI Approved :: MIT License
Classifier: Operating System :: OS Independent
Classifier: Programming Language :: Python :: 3
Requires-Python: >=3.7
